workercontext/__init__.py
workercontext/multiworker.py
workercontext/reductions.py
workercontext-0.1.1.dist-info/LICENSE
workercontext-0.1.1.dist-info/METADATA
workercontext-0.1.1.dist-info/WHEEL
workercontext-0.1.1.dist-info/top_level.txt
workercontext-0.1.1.dist-info/RECORD
