Metadata-Version: 2.1
Name: workercontext
Version: 0.1.1
Summary: A small package that provides a context to spin up multiple workers to execute a function
Author-email: Owen Elliott <none@none.com>
License: MIT License
Project-URL: Homepage, https://github.com/OwenPendrighElliott/MultiWorker
Project-URL: Bug Tracker, https://github.com/OwenPendrighElliott/MultiWorker/issues
Classifier: Programming Language :: Python :: 3
Classifier: License :: OSI Approved :: MIT License
Classifier: Operating System :: OS Independent
Requires-Python: >=3.7
License-File: LICENSE
